[
  { "name": "Star Sports",
    "img": "https://vel9.velayudhan.me/IPLUpdates/live/256x256bb.jpg",
    "link": "https://vel9.velayudhan.me/IPLUpdates/stream/index.html",
    "srn": "0"
  },
  { "name": "Gazi Tv",
    "img": "https://vel9.velayudhan.me/IPLUpdates/live/256x256bb.jpg",
    "link": "https://vel9.velayudhan.me/IPLUpdates/stream/index.html",
    "srn": "0"
  },
  { "name": "Super Sport",
    "img": "https://vel9.velayudhan.me/IPLUpdates/live/256x256bb.jpg",
    "link": "https://vel9.velayudhan.me/IPLUpdates/stream/index.html",
    "srn": "0"
  },
  { "name": "Willow HD",
    "img": "https://vel9.velayudhan.me/IPLUpdates/live/256x256bb.jpg",
    "link": "https://vel9.velayudhan.me/IPLUpdates/stream/index.html",
    "srn": "0"
  },
  { "name": "Channel9",
    "img": "https://vel9.velayudhan.me/IPLUpdates/live/256x256bb.jpg",
    "link": "https://vel9.velayudhan.me/IPLUpdates/stream/index.html",
    "srn": "0"
  }
]
